pyqt_mvc_w_designer/Abstract_Ctrlr.py
pyqt_mvc_w_designer/Callback_Log_Handler.py
pyqt_mvc_w_designer/Example_Ctrlr.py
pyqt_mvc_w_designer/GUI_Runner.py
pyqt_mvc_w_designer/Main_Win_Ctrlr.py
pyqt_mvc_w_designer/Mpl_Canvas.py
pyqt_mvc_w_designer/Mpl_Ctrlr.py
pyqt_mvc_w_designer/__init__.py
pyqt_mvc_w_designer/ui.py
pyqt_mvc_w_designer-1.0.4.dist-info/LICENSE
pyqt_mvc_w_designer-1.0.4.dist-info/METADATA
pyqt_mvc_w_designer-1.0.4.dist-info/WHEEL
pyqt_mvc_w_designer-1.0.4.dist-info/top_level.txt
pyqt_mvc_w_designer-1.0.4.dist-info/RECORD
