Metadata-Version: 2.1
Name: pyqt-mvc-w-designer
Version: 1.0.4
Summary: Framework for the Model-View-Controller GUI pattern using PyQt with Qt Designer
Home-page: https://github.com/rgill02/pyqt-mvc-w-designer
Author: Ryan Gill
Author-email: ryansoftwaredev@gmail.com
Project-URL: Bug Tracker, https://github.com/rgill02/pyqt-mvc-w-designer/issues
Classifier: Programming Language :: Python :: 3
Classifier: License :: OSI Approved :: MIT License
Classifier: Operating System :: OS Independent
Requires-Python: >=3.10
License-File: LICENSE
Requires-Dist: numpy
Requires-Dist: matplotlib
Requires-Dist: PyQt5
